{
	"db":{
		"host":"127.0.0.1",
		"port":12,
		"dbname":"warehouse",
		"connectionString":"mongodb://127.0.0.1/myapp",
		"username": "myapp",
		"password": "myapp"
	},
	"redis":{
		"host":"127.0.0.1",
		"port": 6379,
		"connect_timeout": 360000
	},
	"es":{
		"logsTrace":{
			"host": "localhost:9200",
			"index": "applogs",
			"type": "logger"
		}
	},
	"settings":{
		"isConsole": true,
		"isElasticLogger": false
	},
	"sendgridKey": "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"
}